aiolmdb/__init__.py
aiolmdb/coders.py
tests/__init__.py
tests/test_aiolmdb.py
tests/test_coders.py
tests/testlib.py
aiolmdb-0.1.0.dist-info/LICENSE
aiolmdb-0.1.0.dist-info/METADATA
aiolmdb-0.1.0.dist-info/WHEEL
aiolmdb-0.1.0.dist-info/top_level.txt
aiolmdb-0.1.0.dist-info/RECORD
