Metadata-Version: 2.1
Name: aiolmdb
Version: 0.1.0
Summary: An asyncio wrapper around Lighting Memory Mapped Database (LMDB)
Home-page: https://github.com/pypa/sampleproject
Author: James Liu
Author-email: contact@jamessliu.com
License: UNKNOWN
Platform: UNKNOWN
Classifier: Programming Language :: Python :: 3
Classifier: License :: OSI Approved :: MIT License
Classifier: Operating System :: OS Independent
